silly_voice_lab/__init__.py
silly_voice_lab/main.py
silly_voice_lab/src/__init__.py
silly_voice_lab/src/generator.py
silly_voice_lab/src/helpers.py
silly_voice_lab/src/models.py
silly_voice_lab/src/tts_converters.py
silly_voice_lab/src/init_project/expert/Makefile
silly_voice_lab/src/init_project/expert/configs/dev_process.cfg
silly_voice_lab/src/init_project/expert/configs/prod_process.cfg
silly_voice_lab/src/init_project/expert/configs/text_process.cfg
silly_voice_lab/src/init_project/expert/scenario/heroes.yaml
silly_voice_lab/src/init_project/init/silly_voice_lab.cfg
silly_voice_lab/src/init_project/init/scenario/heroes.yaml
silly_voice_lab/src/init_project/init/scenario/npcs.yaml
silly_voice_lab/src/init_project/init/scenario/heroes/John/actions.yaml
silly_voice_lab/src/init_project/init/scenario/heroes/Sarah/actions.yaml
silly_voice_lab-0.2.3.dist-info/METADATA
silly_voice_lab-0.2.3.dist-info/WHEEL
silly_voice_lab-0.2.3.dist-info/entry_points.txt
silly_voice_lab-0.2.3.dist-info/top_level.txt
silly_voice_lab-0.2.3.dist-info/RECORD
