Metadata-Version: 2.4
Name: silly-voice-lab
Version: 0.2.3
Summary: Dialogues voice generator using ElevenLabs (AI)
Author-email: Vincent Fabre <peigne.plume@gmail.com>
License-Expression: MIT
Project-URL: Homepage, https://github.com/byoso/ElevenLabs-tools
Project-URL: Repository, https://github.com/byoso/ElevenLabs-tools
Keywords: silly-voice-lab,voice,elevenlabs
Classifier: Programming Language :: Python :: 3
Classifier: Development Status :: 5 - Production/Stable
Classifier: Natural Language :: English
Requires-Python: >=3.10
Requires-Dist: pydub<1.0.0,>=0.25.1
Requires-Dist: pyttsx3<3.0.0,>=2.99
Requires-Dist: PyYAML<7.0.0,>=6.0.2
Requires-Dist: requests<3.0.0,>=2.32.4
